{
  "appPageId" : "61658b33-d1e0-4dc5-9ec5-b318beb0038e",
  "componentName" : "siteforce:sldsOneColLayout",
  "dataProviders" : [ ],
  "id" : "a1b36435-8c37-48c5-9fb0-63a926896b54",
  "label" : "Stream List",
  "regions" : [ {
    "components" : [ {
      "componentAttributes" : { },
      "componentName" : "forceCommunity:streamList",
      "id" : "90c852bf-2951-4229-b4b5-590c2490ea08",
      "renderPriority" : "NEUTRAL",
      "renditionMap" : { },
      "type" : "component"
    } ],
    "id" : "18859fe7-2c41-49b4-9285-6db212901d1a",
    "regionName" : "content",
    "type" : "region"
  } ],
  "themeLayoutType" : "Inner",
  "type" : "view",
  "viewType" : "list-0Fq"
}